{
  "sujeto": {
    "sujetoNif": "12345678Z",
    "sujetoNombreCompletoRazonSocial": "María García López",
    "sujetoNombreVia": "Avinguda Diagonal",
    "sujetoNumeroVia": "456",
    "sujetoEscalera": "B",
    "sujetoPiso": "3",
    "sujetoPuerta": "2",
    "sujetoCodigoPostal": "08008",
    "sujetoMunicipio": "Barcelona",
    "sujetoProvincia": "Barcelona",
    "sujetoPais": "ES",
    "sujetoTelefono": "934123456",
    "sujetoCorreoElectronico": "maria.garcia@example.com",
    "sujetoFechaNacimiento": "1985-03-15",
    "sujetoParentesco": "Hija",
    "sujetoGrupoParentesco": "I",
    "sujetoPatrimonioPreexistente": 0.0,
    "sujetoTieneDiscapacidad": false,
    "sujetoPorcentajeDiscapacidad": null,
    "sujetoTituloSucesorio": "Heredera"
  },
  "fallecido": {
    "fallecidoNif": "87654321A",
    "fallecidoNombreCompleto": "José García Martínez",
    "fallecidoNombreVia": "Carrer de la Pau",
    "fallecidoNumeroVia": "23",
    "fallecidoEscalera": null,
    "fallecidoPiso": "1",
    "fallecidoPuerta": "A",
    "fallecidoCodigoPostal": "08002",
    "fallecidoMunicipio": "Barcelona",
    "fallecidoProvincia": "Barcelona",
    "fallecidoPais": "ES",
    "fallecidoObligadoImpuestoPatrimonioUltimosCuatroAnos": false,
    "fallecidoEsTestamentaria": true,
    "fallecidoEsIntestada": false,
    "fallecidoNumeroPersonasInteresadas": 1,
    "fallecidoNotarioOAutoridad": "Notario Joan Puig",
    "fallecidoFechaActaNotarial": "2024-10-15"
  },
  "reconocimiento": {
    "reconocimientoNifFirmante": "12345678Z",
    "reconocimientoNombreCompletoFirmante": "María García López",
    "reconocimientoNombreVia": "Avinguda Diagonal",
    "reconocimientoNumeroVia": "456",
    "reconocimientoEscalera": "B",
    "reconocimientoPiso": "3",
    "reconocimientoPuerta": "2",
    "reconocimientoCodigoPostal": "08008",
    "reconocimientoMunicipio": "Barcelona",
    "reconocimientoProvincia": "Barcelona",
    "reconocimientoPais": "ES",
    "reconocimientoTelefono": "934123456",
    "reconocimientoCorreoElectronico": "maria.garcia@example.com",
    "reconocimientoAcuerdoDeclaracion": true,
    "reconocimientoFechaFirma": "2024-11-20"
  },
  "pago": {
    "pagoIban": "ES9121000418450200051332",
    "pagoCargoEnCuenta": true,
    "pagoPagoEfectivo": false,
    "pagoPaisBanco": "ES",
    "pagoDigitosControlBanco": "91",
    "pagoEntidadBanco": "2100",
    "pagoSucursalBanco": "0418",
    "pagoDigitosControlBanco2": "45",
    "pagoNumeroCuenta": "0200051332",
    "pagoImporte": 45000.0
  },
  "liquidacion": {
    "liquidacionBonificacionDiscapacidad": 0.0,
    "liquidacionCuotaTributariaCasoGeneral": 45000.0,
    "liquidacionTipoMedioEfectivoCuotaTributaria": 0.0,
    "liquidacionBaseLiquidableRealCaja13": 300000.0,
    "liquidacionBaseLiquidableTeoricaCaja14": 300000.0,
    "liquidacionCuotaIntegraCaja16": 45000.0,
    "liquidacionCuotaTributariaCaja605": 45000.0,
    "liquidacionReduccionExcesoCuotaCaja606": 0.0,
    "liquidacionCuotaTributariaAjustadaCaja607": 45000.0,
    "liquidacionTipoMedioEfectivoCaja17": 15.0,
    "liquidacionCuotaTributariaAjustadaCaja18": 45000.0,
    "liquidacionBonificacionCuotaCaja19": 0.0,
    "liquidacionDeduccionDobleImposicionCaja20": 0.0,
    "liquidacionDeduccionCuotasAnterioresCaja21": 0.0,
    "liquidacionCuotaIngresarCaja22": 45000.0,
    "liquidacionRecargoCaja23": 0.0,
    "liquidacionInteresesDemoraCaja24": 0.0,
    "liquidacionTotalIngresarCaja25": 45000.0
  },
  "reducciones": [],
  "totalesReducciones": {
    "totalReduccionesRealCaja11": 0.0,
    "totalReduccionesTeoricaCaja12": 0.0,
    "totalReduccionesAplicadas": 0.0
  }
}

